citation_map/__init__.py
citation_map/citation_map.py
citation_map/scholarly_support.py
citation_map-5.0.dist-info/LICENSE.md
citation_map-5.0.dist-info/METADATA
citation_map-5.0.dist-info/WHEEL
citation_map-5.0.dist-info/top_level.txt
citation_map-5.0.dist-info/RECORD
