Metadata-Version: 2.1
Name: citation-map
Version: 5.0
Summary: A simple tool to generate your Google Scholar citation world map.
Home-page: https://github.com/ChenLiu-1996/CitationMap
Author: Chen Liu
Author-email: chen.liu.cl2482@yale.edu
License: CC BY-NC-SA
Keywords: citation map,citation world map,google scholar
Classifier: Development Status :: 3 - Alpha
Classifier: Intended Audience :: Developers
Classifier: License :: Other/Proprietary License
Classifier: Programming Language :: Python :: 3
License-File: LICENSE.md
Requires-Dist: scholarly
Requires-Dist: geopy
Requires-Dist: folium
Requires-Dist: tqdm
Requires-Dist: selenium
Requires-Dist: bs4
Requires-Dist: pycountry
Requires-Dist: pandas
